star_lord/__init__.py
star_lord/base_model.py
star_lord/delete_model.py
star_lord/amqp/__init__.py
star_lord/amqp/config.py
star_lord/amqp/job.py
star_lord/amqp/start.py
star_lord/management/__init__.py
star_lord/management/commands/__init__.py
star_lord/management/commands/makemigrations.py
star_lord/management/commands/migrate.py
star_lord/management/commands/tasks.py
star_lord/utils/__init__.py
star_lord/utils/producer.py
star_lord/utils/utils.py
star_lord-0.0.47.dist-info/LICENSE
star_lord-0.0.47.dist-info/METADATA
star_lord-0.0.47.dist-info/WHEEL
star_lord-0.0.47.dist-info/top_level.txt
star_lord-0.0.47.dist-info/RECORD
