Metadata-Version: 2.1
Name: star-lord
Version: 0.0.47
Summary: Microservice with django
Home-page: https://github.com/wienerdeming/star-lord
License: UNKNOWN
Platform: UNKNOWN
Classifier: Programming Language :: Python :: 3
Classifier: License :: OSI Approved :: MIT License
Classifier: Operating System :: OS Independent
Requires-Python: >=3.5
